PS6/FSM_After.v
`timescale 1ns / 1ns

module FSM_After(Y, X, reset, clk);

output reg [0:0]Y;
input wire X;
input wire reset;
input wire clk;

parameter S0 = 2'b00,
	S1S2 = 2'b01,
	S3 = 2'b11;
	
reg [1:0] currentState;
reg [1:0] nextState;

initial begin
	currentState <= S0;
end

always@(X, currentState) begin
	case(currentState)
		S0: begin
			if(X == 0) begin
				nextState <= S0;
				Y <= 1'b0;
			end
			else begin
				nextState <= S1S2;
				Y <= 1'b1;
			end
		end
		S1S2: begin
			if(X == 0) begin
				nextState <= S3;
				Y <= 1'b1;
			end
			else begin
				nextState <= S1S2;
				Y <= 1'b0;
			end
		end
		S3: begin
			if(X == 0) begin
				nextState <= S0;
				Y <= 1'b1;
			end
			else begin
				nextState <= S3;
				Y <= 1'b0;
			end
		end
	endcase
end
		
always@(posedge clk) begin
	if(reset) begin
		currentState <= S0;
	end
	else begin
		currentState <= nextState;
	end
end

endmodule

PS6/FSM_After_Testbench.v
`timescale 1ns/1ns
module testbench();

wire [0:0] Y;

reg X;
reg reset;
reg clk;

FSM_After fsm(Y, X, reset, clk);

initial begin
    $dumpfile("TimingDiagram.vcd");
    $dumpvars(0, fsm, Y, X, reset, clk);
    
    reset = 1;
    X = 0;
    #30;
    reset = 0;
	X = 0;
    #40;
	X = 1;
    #40;
	X = 1;
    #40;
	X = 1;
    #40;
	X = 1;
    #40;
	X = 0;
    #40;
	X = 0;
    #40;
	X = 1;
    #40;
	
	#80;
	
    $finish;
end

always begin	
	clk = 0;
	#20;
	clk = 1;
	#20;
    end

endmodule

PS6/TimingDiagram.vcd
$date
	Tue Apr 21 14:46:57 2020
$end
$version
	Icarus Verilog
$end
$timescale
	1ns
$end
$scope module testbench $end
$scope module fsm $end
$var wire 1 ! X $end
$var wire 1 " clk $end
$var wire 1 # reset $end
$var reg 1 $ Y $end
$var reg 2 % currentState [1:0] $end
$var reg 2 & nextState [1:0] $end
$upscope $end
$upscope $end
$scope module testbench $end
$var wire 1 $ Y $end
$upscope $end
$scope module testbench $end
$var reg 1 ! X $end
$upscope $end
$scope module testbench $end
$var reg 1 # reset $end
$upscope $end
$scope module testbench $end
$var reg 1 " clk $end
$upscope $end
$enddefinitions $end
#0
$dumpvars
b0 &
b0 %
0$
1#
0"
0!
$end
#20
1"
#30
0#
#40
0"
#60
1"
#70
1$
b1 &
1!
#80
0"
#100
0$
b10 &
b1 %
1"
#120
0"
#140
b1 &
b10 %
1"
#160
0"
#180
b10 &
b1 %
1"
#200
0"
#220
b1 &
b10 %
1"
#230
1$
b11 &
0!
#240
0"
#260
b0 &
b11 %
1"
#280
0"
#300
0$
b0 %
1"
#310
1$
b1 &
1!
#320
0"
#340
0$
b10 &
b1 %
1"
#360
0"
#380
b1 &
b10 %
1"
#400
0"
#420
b10 &
b1 %
1"
