pre1/ep2.v
`timescale 1ns/1ns
module ep2(s,u,r,g,x);

    input u,r,g,x;
    wire wRG,wURG;
    output s;

    or(wRG,r,g);
    and(wURG,wRG,u);
    or(s,wURG,x);


endmodule

pre1/ep2Bechmark.v
`timescale 1ns/1ns

module ep2Bechmark();
    reg u,r,g,x;
    wire s;

    ep2 xp(s,u,r,g,x);

    initial
        begin
            $dumpfile("test.vcd");
            $dumpvars(0,s,u,r,g,x);
            u = 0;
            r = 0;
            g = 0;
            x = 0;
            #20
            u = 0;
            r = 0;
            g = 0;
            x = 1;
            #20
            u = 0;
            r = 0;
            g = 1;
            x = 0;
            #20
            u = 0;
            r = 0;
            g = 1;
            x = 1;
            #20
            u = 0;
            r = 1;
            g = 0;
            x = 0;
            #20
            u = 0;
            r = 1;
            g = 0;
            x = 1;
            #20
            u = 0;
            r = 1;
            g = 1;
            x = 0;
            #20
            u = 0;
            r = 1;
            g = 1;
            x = 1;
            #20
            u = 1;
            r = 0;
            g = 0;
            x = 0;
            #20
            u = 1;
            r = 0;
            g = 0;
            x = 1;
            #20
            u = 1;
            r = 0;
            g = 1;
            x = 0;
            #20
            u = 1;
            r = 0;
            g = 1;
            x = 1;
            #20
            u = 1;
            r = 1;
            g = 0;
            x = 0;
            #20
            u = 1;
            r = 1;
            g = 0;
            x = 1;
            #20
            u = 1;
            r = 1;
            g = 1;
            x = 0;
            #20
            u = 1;
            r = 1;
            g = 1;
            x = 1;
            #20

            $finish;

        end

endmodule

pre1/test.vcd
$date
	Tue Mar  3 20:59:48 2020
$end
$version
	Icarus Verilog
$end
$timescale
	1ns
$end
$scope module ep2Bechmark $end
$var wire 1 ! s $end
$upscope $end
$scope module ep2Bechmark $end
$var reg 1 " u $end
$upscope $end
$scope module ep2Bechmark $end
$var reg 1 # r $end
$upscope $end
$scope module ep2Bechmark $end
$var reg 1 $ g $end
$upscope $end
$scope module ep2Bechmark $end
$var reg 1 % x $end
$upscope $end
$enddefinitions $end
#0
$dumpvars
0%
0$
0#
0"
0!
$end
#20
1!
1%
#40
0!
0%
1$
#60
1!
1%
#80
0!
0%
0$
1#
#100
1!
1%
#120
0!
0%
1$
#140
1!
1%
#160
0!
0%
0$
0#
1"
#180
1!
1%
#200
1!
0%
1$
#220
1%
#240
0%
0$
1#
#260
1%
#280
0%
1$
#300
1%
