pre5/FSM.v
`timescale 1ns / 1ns

module FSM(Y, X, reset, clk);

output reg [1:0]Y;
input wire X;
input wire reset;
input wire clk;

parameter S0 = 2'b00,
	S1 = 2'b01,
	S2 = 2'b10,
	S3 = 2'b11;
	
reg [1:0] currentState;
reg [1:0] nextState;

initial begin
	currentState <= S0;
end

always@(X, currentState) begin
	case(currentState)
		S0: begin
			if(X == 0) begin
				nextState <= S0;
				Y <= 2'b01;
			end
			else begin
				nextState <= S2;
				Y <= 2'b00;
			end
		end
		S1: begin
			if(X == 0) begin
				nextState <= S0;
				Y <= 2'b00;
			end
			else begin
				nextState <= S1;
				Y <= 2'b01;
			end
		end
		S2: begin
			if(X == 0) begin
				nextState <= S1;
				Y <= 2'b10;
			end
			else begin
				nextState <= S0;
				Y <= 2'b00;
			end
		end
		S3: begin
			if(X == 0) begin
				nextState <= S3;
				Y <= 2'b10;
			end
			else begin
				nextState <= S3;
				Y <= 2'b00;
			end
		end
	endcase
end
		
always@(posedge clk) begin
	if(reset) begin
		currentState <= S0;
	end
	else begin
		currentState <= nextState;
	end
end

endmodule

pre5/FSM_Testbench.v
`timescale 1ns/1ns
module testbench();

wire [1:0] Y;

reg X;
reg reset;
reg clk;

FSM fsm(Y, X, reset, clk);

initial begin
    $dumpfile("TimingDiagram.vcd");
    $dumpvars(0, fsm, Y, X, reset, clk);
    
    reset = 1;
    X = 0;
    #30;
    reset = 0;
	X = 0;
    #40;
	X = 1;
    #40;
	X = 1;
    #40;
	X = 1;
    #40;
	X = 1;
    #40;
	X = 0;
    #40;
	X = 0;
    #40;
	X = 1;
    #40;
	
	#80;
	
    $finish;
end

always begin	
	clk = 0;
	#20;
	clk = 1;
	#20;
    end

endmodule

pre5/TimingDiagram.vcd
$date
	Thu Apr 30 16:19:27 2020
$end
$version
	Icarus Verilog
$end
$timescale
	1ns
$end
$scope module testbench $end
$scope module fsm $end
$var wire 1 ! X $end
$var wire 1 " clk $end
$var wire 1 # reset $end
$var reg 2 $ Y [1:0] $end
$var reg 2 % currentState [1:0] $end
$var reg 2 & nextState [1:0] $end
$upscope $end
$upscope $end
$scope module testbench $end
$var wire 2 ' Y [1:0] $end
$upscope $end
$scope module testbench $end
$var reg 1 ! X $end
$upscope $end
$scope module testbench $end
$var reg 1 # reset $end
$upscope $end
$scope module testbench $end
$var reg 1 " clk $end
$upscope $end
$enddefinitions $end
#0
$dumpvars
b1 '
b0 &
b0 %
b1 $
1#
0"
0!
$end
#20
1"
#30
0#
#40
0"
#60
1"
#70
b0 $
b0 '
b10 &
1!
#80
0"
#100
b0 &
b10 %
1"
#120
0"
#140
b10 &
b0 %
1"
#160
0"
#180
b0 &
b10 %
1"
#200
0"
#220
b10 &
b0 %
1"
#230
b1 $
b1 '
b0 &
0!
#240
0"
#260
1"
#280
0"
#300
1"
#310
b0 $
b0 '
b10 &
1!
#320
0"
#340
b0 &
b10 %
1"
#360
0"
#380
b10 &
b0 %
1"
#400
0"
#420
b0 &
b10 %
1"
