pre2/multiplexer.v
`timescale 1ns / 1ns
module multiplexer81(
	output reg Y,
	input [0:7] X,
	input [2:0] S
);

always @(*) begin
	case(S)
		3'b000: Y <= X[0];
		3'b001: Y <= X[1];
		3'b010: Y <= X[2];
		3'b011: Y <= X[3];
		3'b100: Y <= X[4];
		3'b101: Y <= X[5];
		3'b110: Y <= X[6];

		default: Y <= X[7];
	endcase
end

endmodule

pre2/decoder.v
`timescale 1ns / 1ns
module decoder24(
	output reg [3:0] Y,
	input [1:0] X
);

always @(*) begin
	case(X)
		2'b00: Y <= 4'b0001;
		2'b01: Y <= 4'b0010;
		2'b10: Y <= 4'b0100;
		default: Y <= 4'b0000;
	endcase
end

endmodule

pre2/multiplexerTest.v
`timescale 1ns / 1ns
module TestBench();

wire OutputMux;
reg [2:0] SelectionMux;


reg [1:0] inputDecoder;
wire [3:0] outputDecoder;


decoder24 decoder24(outputDecoder, inputDecoder);
wire zeroInput;
wire threeOutput;
wire zeroOneInput;
wire twoOutput;
wire notThreeOutput;
not(zeroInput,inputDecoder[1]);
or(threeOutput,inputDecoder[0],inputDecoder[1]);
not(notThreeOutput,threeOutput);
not(twoOutput,outputDecoder[1]);
xnor(zeroOneInput,inputDecoder[1],inputDecoder[0]);



multiplexer81 multiplexer81(OutputMux, {1'b0,zeroInput,twoOutput,notThreeOutput,inputDecoder[1],notThreeOutput,threeOutput,zeroOneInput}, SelectionMux);



initial begin
	$dumpfile("test.vcd");
	$dumpvars(0, OutputMux, inputDecoder, SelectionMux);
	
	inputDecoder = 2'b00; SelectionMux = 3'b000;
	#20;
    inputDecoder = 2'b01; SelectionMux = 3'b000;
	#20;
    inputDecoder = 2'b10; SelectionMux = 3'b000;
	#20;
    inputDecoder = 2'b11; SelectionMux = 3'b000;
	#20;
    inputDecoder = 2'b00; SelectionMux = 3'b001;
	#20;
    inputDecoder = 2'b01; SelectionMux = 3'b001;
	#20;
    inputDecoder = 2'b10; SelectionMux = 3'b001;
	#20;
    inputDecoder = 2'b11; SelectionMux = 3'b001;
	#20;
	inputDecoder = 2'b00; SelectionMux = 3'b010;
	#20;
    inputDecoder = 2'b01; SelectionMux = 3'b010;
	#20;
    inputDecoder = 2'b10; SelectionMux = 3'b010;
	#20;
    inputDecoder = 2'b11; SelectionMux = 3'b010;
	#20;
    inputDecoder = 2'b00; SelectionMux = 3'b011;
	#20;
    inputDecoder = 2'b01; SelectionMux = 3'b011;
	#20;
    inputDecoder = 2'b10; SelectionMux = 3'b011;
	#20;
    inputDecoder = 2'b11; SelectionMux = 3'b011;
	#20;
	
    inputDecoder = 2'b00; SelectionMux = 3'b100;
	#20;
    inputDecoder = 2'b01; SelectionMux = 3'b100;
	#20;
    inputDecoder = 2'b10; SelectionMux = 3'b100;
	#20;
    inputDecoder = 2'b11; SelectionMux = 3'b100;
	#20;
    inputDecoder = 2'b00; SelectionMux = 3'b101;
	#20;
    inputDecoder = 2'b01; SelectionMux = 3'b101;
	#20;
    inputDecoder = 2'b10; SelectionMux = 3'b101;
	#20;
    inputDecoder = 2'b11; SelectionMux = 3'b101;
	#20;
	inputDecoder = 2'b00; SelectionMux = 3'b110;
	#20;
    inputDecoder = 2'b01; SelectionMux = 3'b110;
	#20;
    inputDecoder = 2'b10; SelectionMux = 3'b110;
	#20;
    inputDecoder = 2'b11; SelectionMux = 3'b110;
	#20;
    inputDecoder = 2'b00; SelectionMux = 3'b111;
	#20;
    inputDecoder = 2'b01; SelectionMux = 3'b111;
	#20;
    inputDecoder = 2'b10; SelectionMux = 3'b111;
	#20;
    inputDecoder = 2'b11; SelectionMux = 3'b111;
	#20;


	$finish;
end

endmodule

pre2/test.vcd
$date
	Thu Apr 30 16:18:36 2020
$end
$version
	Icarus Verilog
$end
$timescale
	1ns
$end
$scope module TestBench $end
$var wire 1 ! OutputMux $end
$upscope $end
$scope module TestBench $end
$var reg 2 " inputDecoder [1:0] $end
$upscope $end
$scope module TestBench $end
$var reg 3 # SelectionMux [2:0] $end
$upscope $end
$enddefinitions $end
#0
$dumpvars
b0 #
b0 "
0!
$end
#20
b1 "
#40
b10 "
#60
b11 "
#80
1!
b1 #
b0 "
#100
b1 "
#120
0!
b10 "
#140
b11 "
#160
1!
b10 #
b0 "
#180
0!
b1 "
#200
1!
b10 "
#220
b11 "
#240
1!
b11 #
b0 "
#260
0!
b1 "
#280
b10 "
#300
b11 "
#320
b100 #
b0 "
#340
b1 "
#360
1!
b10 "
#380
b11 "
#400
1!
b101 #
b0 "
#420
0!
b1 "
#440
b10 "
#460
b11 "
#480
0!
b110 #
b0 "
#500
1!
b1 "
#520
b10 "
#540
b11 "
#560
b111 #
b0 "
#580
0!
b1 "
#600
b10 "
#620
1!
b11 "
